pyro_simpletk/__init__.py
pyro_simpletk-0.1.2.dist-info/METADATA
pyro_simpletk-0.1.2.dist-info/WHEEL
pyro_simpletk-0.1.2.dist-info/top_level.txt
pyro_simpletk-0.1.2.dist-info/RECORD
